eof_optimization/__init__.py
eof_optimization/eof.py
eof_optimization/slres.py
eof_optimization-0.1.0.dist-info/licenses/LICENSE
eof_optimization-0.1.0.dist-info/METADATA
eof_optimization-0.1.0.dist-info/WHEEL
eof_optimization-0.1.0.dist-info/top_level.txt
eof_optimization-0.1.0.dist-info/RECORD
